humai_tools/__init__.py
humai_tools/campus.py
humai_tools/directus.py
humai_tools/models.py
humai_tools/mp.py
humai_tools/permissions.py
humai_tools/settings.py
humai_tools/utils.py
humai_tools-0.0.5.dist-info/METADATA
humai_tools-0.0.5.dist-info/WHEEL
humai_tools-0.0.5.dist-info/top_level.txt
humai_tools-0.0.5.dist-info/RECORD
